{
  "config": {
    "min_n": 24,
    "max_n": 24,
    "workers": 8,
    "geng": "/opt/homebrew/bin/geng",
    "tol": 1e-12,
    "top_k": 20,
    "out": "results/whnc_extremal_scan_n24.json"
  },
  "per_n": {
    "24": {
      "n": 24,
      "total_trees": 39299897,
      "dleaf_trees": 1232541,
      "whnc_failures": 0,
      "min_margin": 0.0972653557728479,
      "min_g6": "W???????????_?W?I?@O?D??I??I??D??@O??I???g?O@??",
      "top_minimizers": [
        {
          "margin": 0.0972653557728479,
          "g6": "W???????????_?W?I?@O?D??I??I??D??@O??I???g?O@??",
          "is_spider": true,
          "arms": [],
          "is_s2k1_like": false
        },
        {
          "margin": 0.12046283466322633,
          "g6": "W???????????_?O?E?@O?D??I??I??D??@O??I???g?W@??",
          "is_spider": true,
          "arms": [
            2,
            2,
            19
          ],
          "is_s2k1_like": false
        },
        {
          "margin": 0.12602170825877185,
          "g6": "W???????????_?O?C??o?D??I??I??D??@O??I???g?[@??",
          "is_spider": true,
          "arms": [
            2,
            2,
            2,
            17
          ],
          "is_s2k1_like": false
        },
        {
          "margin": 0.1272846629582277,
          "g6": "W???????????_?O?C??_?A??C??C??A???_??E???g?^}??",
          "is_spider": false,
          "arms": null,
          "is_s2k1_like": false
        },
        {
          "margin": 0.12954891269891577,
          "g6": "W???????????_?O?E?@O?`??Q??Q??D??@O??I???g?G`??",
          "is_spider": true,
          "arms": [
            2,
            4,
            17
          ],
          "is_s2k1_like": false
        },
        {
          "margin": 0.13086724794690857,
          "g6": "W???????????_?O?E?@O?`??Q??I??P??AO??I???g?GH??",
          "is_spider": true,
          "arms": [
            2,
            6,
            15
          ],
          "is_s2k1_like": false
        },
        {
          "margin": 0.13105965823606736,
          "g6": "W???????????_?O?E?@O?`??Q??I??P??@O??a??@G?GB??",
          "is_spider": true,
          "arms": [
            2,
            8,
            13
          ],
          "is_s2k1_like": false
        },
        {
          "margin": 0.13108925630305318,
          "g6": "W???????????_?O?E?@O?`??Q??I??P??@O??a???g?GC_?",
          "is_spider": true,
          "arms": [
            2,
            10,
            11
          ],
          "is_s2k1_like": false
        },
        {
          "margin": 0.1311040549849946,
          "g6": "W???????????_?O?E?@O?`??Q??I??P??@O??E???W?GO_?",
          "is_spider": true,
          "arms": [
            2,
            9,
            12
          ],
          "is_s2k1_like": false
        },
        {
          "margin": 0.13117804487940815,
          "g6": "W???????????_?O?E?@O?`??Q??I??B???o??E???W?H?_?",
          "is_spider": true,
          "arms": [
            2,
            7,
            14
          ],
          "is_s2k1_like": false
        },
        {
          "margin": 0.13168102083465255,
          "g6": "W???????????_?O?E?@O?`??E??E??B???o??E???W?I?_?",
          "is_spider": true,
          "arms": [
            2,
            5,
            16
          ],
          "is_s2k1_like": false
        },
        {
          "margin": 0.13201130888384427,
          "g6": "W?????????O?O?G?A??O?@??A??A??@???O??A?Fw???^_?",
          "is_spider": false,
          "arms": null,
          "is_s2k1_like": false
        },
        {
          "margin": 0.13226709944245174,
          "g6": "W???????????_?O?C??_?A??C??C??A???o??I???g?^{??",
          "is_spider": false,
          "arms": null,
          "is_s2k1_like": false
        },
        {
          "margin": 0.13455479395195563,
          "g6": "W???????????_?O?C??_?A??C??C??A???_??E???g?^{?A",
          "is_spider": false,
          "arms": null,
          "is_s2k1_like": false
        },
        {
          "margin": 0.13512061377517548,
          "g6": "W???????????_?O?S?@_?E??K??K??E??@_??K???W?GB??",
          "is_spider": true,
          "arms": [
            2,
            3,
            18
          ],
          "is_s2k1_like": false
        },
        {
          "margin": 0.1362100572032845,
          "g6": "W???????????_?O?C??_?A??C??C??A???o??I???g?^w?C",
          "is_spider": false,
          "arms": null,
          "is_s2k1_like": false
        },
        {
          "margin": 0.14014422728130088,
          "g6": "W???????????_?O?C??_?A??C??C??A???o??I???g?^w?A",
          "is_spider": false,
          "arms": null,
          "is_s2k1_like": false
        },
        {
          "margin": 0.14168958804567966,
          "g6": "W???????????_?O?E?@O?`?@A??a??P??@O??I???g??p??",
          "is_spider": true,
          "arms": [
            4,
            4,
            15
          ],
          "is_s2k1_like": false
        },
        {
          "margin": 0.14181059361541432,
          "g6": "W???????????_?O?C??_?A??C??C??B??@O??I???g?^s??",
          "is_spider": false,
          "arms": null,
          "is_s2k1_like": false
        },
        {
          "margin": 0.1428030640420414,
          "g6": "W???????????_?O?C??o?D?AA??Q??H??@O??I???g?KP??",
          "is_spider": true,
          "arms": [
            2,
            2,
            4,
            15
          ],
          "is_s2k1_like": false
        }
      ]
    }
  },
  "wall_s": 225.51701712608337
}